Workbook

Sheet AdjPrice
A1: Date | B1: VTI | C1: VXUS | D1: VNQ | E1: BND | F1: BNDX | G1: SHV | H1: VT
A2: 44440 | B2: 207.1541 | C2: 54.287476 | D2: 83.780258 | E2: 72.129822 | F2: 46.859577 | G2: 92.392197 | H2: 92.206909
A3: 44470 | B3: 221.00729 | C3: 55.849323 | D3: 89.756325 | E3: 72.180534 | F3: 46.652126 | G3: 92.367149 | H3: 96.951721
A4: 44501 | B4: 217.77953 | C4: 53.472206 | D4: 87.863075 | E4: 72.327873 | F4: 47.145569 | G4: 92.32531 | H4: 94.416321
A5: 44531 | B5: 226.03998 | C5: 55.382423 | D5: 96.390701 | E5: 72.103424 | F5: 46.793289 | G5: 92.350418 | H5: 98.009735
A6: 44562 | B6: 212.34314 | C6: 53.814266 | D6: 88.272987 | E6: 70.614563 | F6: 46.148563 | G6: 92.275154 | H6: 93.521172
A7: 44593 | B7: 207.0629 | C7: 52.280937 | D7: 85.198715 | E7: 69.810921 | F7: 45.568645 | G7: 92.241684 | H7: 90.930191
A8: 44621 | B8: 213.813 | C8: 52.132595 | D8: 90.535515 | E8: 67.889648 | F8: 44.553375 | G8: 92.208221 | H8: 92.644608
A9: 44652 | B9: 194.28841 | C9: 48.746681 | D9: 86.834541 | E9: 65.192612 | F9: 43.216831 | G9: 92.181419 | H9: 85.144493
A10: 44682 | B10: 193.8 | C10: 49.488434 | D10: 82.765991 | E10: 65.733528 | F10: 42.925846 | G10: 92.242538 | H10: 85.565262
A11: 44713 | B11: 177.84782 | C11: 45.559647 | D11: 76.600853 | E11: 64.641014 | F11: 42.186668 | G11: 92.17305 | H11: 78.615875
A12: 44743 | B12: 194.47101 | C12: 47.219261 | D12: 83.20076 | E12: 66.180649 | F12: 43.544399 | G12: 92.254311 | H12: 84.106247
A13: 44774 | B13: 187.22014 | C13: 45.100597 | D13: 78.198296 | E13: 64.329239 | F13: 41.973793 | G13: 92.372551 | H13: 80.6978
... A62: 46266 | B62: 375.26001 | C62: 85.519997 | D62: 90.529999 | E62: 69.980721 | F62: 46.746025 | G62: 110.01102 | H62: 158.45

Sheet Weights
B1: VTI | C1: VXUS | D1: VD | E1: BND | F1: BNDX | G1: SHV | H1: VT | I1: Total
A2: Asset Class | B2: US Equity | C2: Intl Equity | D2: Property | E2: Bonds | F2: Bonds | G2: Cash | H2: Global Equity
A3: Portfolio Weight | B3: 0.25 | C3: 0.15 | D3: 0.1 | E3: 0.3 | F3: 0.15 | G3: 0.05 | H3: 0 | I3: =SUM(B3:H3) -> 1
A4: Benchmark Weight | B4: 0 | C4: 0 | D4: 0 | E4: 0.4 | F4: 0 | G4: 0 | H4: 0.6 | I4: =SUM(B4:H4) -> 1

Sheet Calc
A1: Date | B1: VTI | C1: VXUS | D1: VNQ | E1: BND | F1: BNDX | G1: SHV | H1: VT | I1: Portfolio | J1: Benchmark | K1: Excess | L1: Portfolio Index | M1: Benchmark Index | N1: Port Peak | O1: Port Drawdown | P1: Bench Peak | Q1: Bench Drawdown | R1: Port Rolling 12M | S1: Bench Rolling 12M
A2: =AdjPrice!A2 -> 44440 | L2: 100 | M2: 100 | N2: =L2 -> 100 | O2: =L2/N2-1 -> 0 | P2: =M2 -> 100 | Q2: =M2/P2-1 -> 0
A3: =AdjPrice!A3 -> 44470 | B3: =AdjPrice!B3/AdjPrice!B2-1 -> 0.066873865 | C3: =AdjPrice!C3/AdjPrice!C2-1 -> 0.028769945 | D3: =AdjPrice!D3/AdjPrice!D2-1 -> 0.071330248 | E3: =AdjPrice!E3/AdjPrice!E2-1 -> 0.00070307377 | F3: =AdjPrice!F3/AdjPrice!F2-1 -> -0.0044270751 | G3: =AdjPrice!G3/AdjPrice!G2-1 -> -0.00027109759 | H3: =AdjPrice!H3/AdjPrice!H2-1 -> 0.051458313 | I3: =SUMPRODUCT(B3:H3, Weights!$B$3:$H$3) -> 0.027700289 | J3: =SUMPRODUCT(B3:H3, Weights!$B$4:$H$4) -> 0.031156217 | K3: =I3-J3 -> -0.0034559287 | L3: =L2*(1+I3) -> 102.77003 | M3: =M2*(1+J3) -> 103.11562 | N3: =MAX(N2,L3) -> 102.77003 | O3: =L3/N3-1 -> 0 | P3: =MAX(P2,M3) -> 103.11562 | Q3: =M3/P3-1 -> 0
A4: =AdjPrice!A4 -> 44501 | B4: =AdjPrice!B4/AdjPrice!B3-1 -> -0.014604803 | C4: =AdjPrice!C4/AdjPrice!C3-1 -> -0.042563043 | D4: =AdjPrice!D4/AdjPrice!D3-1 -> -0.021093216 | E4: =AdjPrice!E4/AdjPrice!E3-1 -> 0.0020412549 | F4: =AdjPrice!F4/AdjPrice!F3-1 -> 0.010577064 | G4: =AdjPrice!G4/AdjPrice!G3-1 -> -0.00045297056 | H4: =AdjPrice!H4/AdjPrice!H3-1 -> -0.026151164 | I4: =SUMPRODUCT(B4:H4, Weights!$B$3:$H$3) -> -0.0099686912 | J4: =SUMPRODUCT(B4:H4, Weights!$B$4:$H$4) -> -0.014874197 | K4: =I4-J4 -> 0.0049055055 | L4: =L3*(1+I4) -> 101.74555 | M4: =M3*(1+J4) -> 101.58186 | N4: =MAX(N3,L4) -> 102.77003 | O4: =L4/N4-1 -> -0.0099686912 | P4: =MAX(P3,M4) -> 103.11562 | Q4: =M4/P4-1 -> -0.014874197
A5: =AdjPrice!A5 -> 44531 | B5: =AdjPrice!B5/AdjPrice!B4-1 -> 0.037930344 | C5: =AdjPrice!C5/AdjPrice!C4-1 -> 0.035723555 | D5: =AdjPrice!D5/AdjPrice!D4-1 -> 0.097055857 | E5: =AdjPrice!E5/AdjPrice!E4-1 -> -0.003103218 | F5: =AdjPrice!F5/AdjPrice!F4-1 -> -0.0074721691 | G5: =AdjPrice!G5/AdjPrice!G4-1 -> 0.00027195508 | H5: =AdjPrice!H5/AdjPrice!H4-1 -> 0.038059249 | I5: =SUMPRODUCT(B5:H5, Weights!$B$3:$H$3) -> 0.022508512 | J5: =SUMPRODUCT(B5:H5, Weights!$B$4:$H$4) -> 0.021594262 | K5: =I5-J5 -> 0.00091424933 | L5: =L4*(1+I5) -> 104.03569 | M5: =M4*(1+J5) -> 103.77545 | N5: =MAX(N4,L5) -> 104.03569 | O5: =L5/N5-1 -> 0 | P5: =MAX(P4,M5) -> 103.77545 | Q5: =M5/P5-1 -> 0
A6: =AdjPrice!A6 -> 44562 | B6: =AdjPrice!B6/AdjPrice!B5-1 -> -0.060594761 | C6: =AdjPrice!C6/AdjPrice!C5-1 -> -0.02831507 | D6: =AdjPrice!D6/AdjPrice!D5-1 -> -0.084216774 | E6: =AdjPrice!E6/AdjPrice!E5-1 -> -0.020648965 | F6: =AdjPrice!F6/AdjPrice!F5-1 -> -0.013778168 | G6: =AdjPrice!G6/AdjPrice!G5-1 -> -0.00081498253 | H6: =AdjPrice!H6/AdjPrice!H5-1 -> -0.045797119 | I6: =SUMPRODUCT(B6:H6, Weights!$B$3:$H$3) -> -0.036119792 | J6: =SUMPRODUCT(B6:H6, Weights!$B$4:$H$4) -> -0.035737858 | K6: =I6-J6 -> -0.0003819343 | L6: =L5*(1+I6) -> 100.27794 | M6: =M5*(1+J6) -> 100.06673 | N6: =MAX(N5,L6) -> 104.03569 | O6: =L6/N6-1 -> -0.036119792 | P6: =MAX(P5,M6) -> 103.77545 | Q6: =M6/P6-1 -> -0.035737858
A7: =AdjPrice!A7 -> 44593 | B7: =AdjPrice!B7/AdjPrice!B6-1 -> -0.024866558 | C7: =AdjPrice!C7/AdjPrice!C6-1 -> -0.028492984 | D7: =AdjPrice!D7/AdjPrice!D6-1 -> -0.034826873 | E7: =AdjPrice!E7/AdjPrice!E6-1 -> -0.011380687 | F7: =AdjPrice!F7/AdjPrice!F6-1 -> -0.012566326 | G7: =AdjPrice!G7/AdjPrice!G6-1 -> -0.00036272119 | H7: =AdjPrice!H7/AdjPrice!H6-1 -> -0.027704748 | I7: =SUMPRODUCT(B7:H7, Weights!$B$3:$H$3) -> -0.019290566 | J7: =SUMPRODUCT(B7:H7, Weights!$B$4:$H$4) -> -0.021175124 | K7: =I7-J7 -> 0.0018845585 | L7: =L6*(1+I7) -> 98.343521 | M7: =M6*(1+J7) -> 97.947807 | N7: =MAX(N6,L7) -> 104.03569 | O7: =L7/N7-1 -> -0.054713586 | P7: =MAX(P6,M7) -> 103.77545 | Q7: =M7/P7-1 -> -0.056156228
A8: =AdjPrice!A8 -> 44621 | B8: =AdjPrice!B8/AdjPrice!B7-1 -> 0.032599306 | C8: =AdjPrice!C8/AdjPrice!C7-1 -> -0.0028374039 | D8: =AdjPrice!D8/AdjPrice!D7-1 -> 0.062639438 | E8: =AdjPrice!E8/AdjPrice!E7-1 -> -0.027521085 | F8: =AdjPrice!F8/AdjPrice!F7-1 -> -0.022280018 | G8: =AdjPrice!G8/AdjPrice!G7-1 -> -0.00036277009 | H8: =AdjPrice!H8/AdjPrice!H7-1 -> 0.018854205 | I8: =SUMPRODUCT(B8:H8, Weights!$B$3:$H$3) -> 0.0023716931 | J8: =SUMPRODUCT(B8:H8, Weights!$B$4:$H$4) -> 0.0003040893 | K8: =I8-J8 -> 0.0020676038 | L8: =L7*(1+I8) -> 98.576762 | M8: =M7*(1+J8) -> 97.977592 | N8: =MAX(N7,L8) -> 104.03569 | O8: =L8/N8-1 -> -0.052471657 | P8: =MAX(P7,M8) -> 103.77545 | Q8: =M8/P8-1 -> -0.055869215
A9: =AdjPrice!A9 -> 44652 | B9: =AdjPrice!B9/AdjPrice!B8-1 -> -0.091316229 | C9: =AdjPrice!C9/AdjPrice!C8-1 -> -0.064948116 | D9: =AdjPrice!D9/AdjPrice!D8-1 -> -0.040878693 | E9: =AdjPrice!E9/AdjPrice!E8-1 -> -0.039726774 | F9: =AdjPrice!F9/AdjPrice!F8-1 -> -0.029998716 | G9: =AdjPrice!G9/AdjPrice!G8-1 -> -0.00029066891 | H9: =AdjPrice!H9/AdjPrice!H8-1 -> -0.080955758 | I9: =SUMPRODUCT(B9:H9, Weights!$B$3:$H$3) -> -0.053091517 | J9: =SUMPRODUCT(B9:H9, Weights!$B$4:$H$4) -> -0.064464165 | K9: =I9-J9 -> 0.011372648 | L9: =L8*(1+I9) -> 93.343172 | M9: =M8*(1+J9) -> 91.661549 | N9: =MAX(N8,L9) -> 104.03569 | O9: =L9/N9-1 -> -0.10277737 | P9: =MAX(P8,M9) -> 103.77545 | Q9: =M9/P9-1 -> -0.11673182
A10: =AdjPrice!A10 -> 44682 | B10: =AdjPrice!B10/AdjPrice!B9-1 -> -0.0025138058 | C10: =AdjPrice!C10/AdjPrice!C9-1 -> 0.015216474 | D10: =AdjPrice!D10/AdjPrice!D9-1 -> -0.046854052 | E10: =AdjPrice!E10/AdjPrice!E9-1 -> 0.0082972047 | F10: =AdjPrice!F10/AdjPrice!F9-1 -> -0.0067331431 | G10: =AdjPrice!G10/AdjPrice!G9-1 -> 0.00066303036 | H10: =AdjPrice!H10/AdjPrice!H9-1 -> 0.0049418198 | I10: =SUMPRODUCT(B10:H10, Weights!$B$3:$H$3) -> -0.001519044 | J10: =SUMPRODUCT(B10:H10, Weights!$B$4:$H$4) -> 0.0062839737 | K10: =I10-J10 -> -0.0078030177 | L10: =L9*(1+I10) -> 93.20138 | M10: =M9*(1+J10) -> 92.237547 | N10: =MAX(N9,L10) -> 104.03569 | O10: =L10/N10-1 -> -0.10414029 | P10: =MAX(P9,M10) -> 103.77545 | Q10: =M10/P10-1 -> -0.11118138
A11: =AdjPrice!A11 -> 44713 | B11: =AdjPrice!B11/AdjPrice!B10-1 -> -0.082312584 | C11: =AdjPrice!C11/AdjPrice!C10-1 -> -0.079387989 | D11: =AdjPrice!D11/AdjPrice!D10-1 -> -0.074488786 | E11: =AdjPrice!E11/AdjPrice!E10-1 -> -0.016620347 | F11: =AdjPrice!F11/AdjPrice!F10-1 -> -0.017219875 | G11: =AdjPrice!G11/AdjPrice!G10-1 -> -0.00075332408 | H11: =AdjPrice!H11/AdjPrice!H10-1 -> -0.081217382 | I11: =SUMPRODUCT(B11:H11, Weights!$B$3:$H$3) -> -0.047541974 | J11: =SUMPRODUCT(B11:H11, Weights!$B$4:$H$4) -> -0.055378568 | K11: =I11-J11 -> 0.0078365938 | L11: =L10*(1+I11) -> 88.770402 | M11: =M10*(1+J11) -> 87.129564 | N11: =MAX(N10,L11) -> 104.03569 | O11: =L11/N11-1 -> -0.14673123 | P11: =MAX(P10,M11) -> 103.77545 | Q11: =M11/P11-1 -> -0.16040289
A12: =AdjPrice!A12 -> 44743 | B12: =AdjPrice!B12/AdjPrice!B11-1 -> 0.093468584 | C12: =AdjPrice!C12/AdjPrice!C11-1 -> 0.036427292 | D12: =AdjPrice!D12/AdjPrice!D11-1 -> 0.086159705 | E12: =AdjPrice!E12/AdjPrice!E11-1 -> 0.023818233 | F12: =AdjPrice!F12/AdjPrice!F11-1 -> 0.032183885 | G12: =AdjPrice!G12/AdjPrice!G11-1 -> 0.00088160998 | H12: =AdjPrice!H12/AdjPrice!H11-1 -> 0.069837952 | I12: =SUMPRODUCT(B12:H12, Weights!$B$3:$H$3) -> 0.049464343 | J12: =SUMPRODUCT(B12:H12, Weights!$B$4:$H$4) -> 0.051430064 | K12: =I12-J12 -> -0.0019657209 | L12: =L11*(1+I12) -> 93.161372 | M12: =M11*(1+J12) -> 91.610643 | N12: =MAX(N11,L12) -> 104.03569 | O12: =L12/N12-1 -> -0.10452485 | P12: =MAX(P11,M12) -> 103.77545 | Q12: =M12/P12-1 -> -0.11722235
A13: =AdjPrice!A13 -> 44774 | B13: =AdjPrice!B13/AdjPrice!B12-1 -> -0.037285094 | C13: =AdjPrice!C13/AdjPrice!C12-1 -> -0.044868635 | D13: =AdjPrice!D13/AdjPrice!D12-1 -> -0.060125224 | E13: =AdjPrice!E13/AdjPrice!E12-1 -> -0.027975095 | F13: =AdjPrice!F13/AdjPrice!F12-1 -> -0.036069076 | G13: =AdjPrice!G13/AdjPrice!G12-1 -> 0.0012816784 | H13: =AdjPrice!H13/AdjPrice!H12-1 -> -0.040525495 | I13: =SUMPRODUCT(B13:H13, Weights!$B$3:$H$3) -> -0.035802897 | J13: =SUMPRODUCT(B13:H13, Weights!$B$4:$H$4) -> -0.035505335 | K13: =I13-J13 -> -0.00029756214 | L13: =L12*(1+I13) -> 89.825925 | M13: =M12*(1+J13) -> 88.357977 | N13: =MAX(N12,L13) -> 104.03569 | O13: =L13/N13-1 -> -0.13658546 | P13: =MAX(P12,M13) -> 103.77545 | Q13: =M13/P13-1 -> -0.14856567
A14: =AdjPrice!A14 -> 44805 | B14: =AdjPrice!B14/AdjPrice!B13-1 -> -0.092304766 | C14: =AdjPrice!C14/AdjPrice!C13-1 -> -0.099058002 | D14: =AdjPrice!D14/AdjPrice!D13-1 -> -0.12871323 | E14: =AdjPrice!E14/AdjPrice!E13-1 -> -0.041829988 | F14: =AdjPrice!F14/AdjPrice!F13-1 -> -0.028930914 | G14: =AdjPrice!G14/AdjPrice!G13-1 -> 0.00028205762 | H14: =AdjPrice!H14/AdjPrice!H13-1 -> -0.095289576 | I14: =SUMPRODUCT(B14:H14, Weights!$B$3:$H$3) -> -0.067680745 | J14: =SUMPRODUCT(B14:H14, Weights!$B$4:$H$4) -> -0.073905741 | K14: =I14-J14 -> 0.0062249956 | L14: =L13*(1+I14) -> 83.746439 | M14: =M13*(1+J14) -> 81.827815 | N14: =MAX(N13,L14) -> 104.03569 | O14: =L14/N14-1 -> -0.195022 | P14: =MAX(P13,M14) -> 103.77545 | Q14: =M14/P14-1 -> -0.21149155 | R14: =L14/L2-1 -> -0.16253561 | S14: =M14/M2-1 -> -0.18172185
A15: =AdjPrice!A15 -> 44835 | B15: =AdjPrice!B15/AdjPrice!B14-1 -> 0.081127682 | C15: =AdjPrice!C15/AdjPrice!C14-1 -> 0.034083376 | D15: =AdjPrice!D15/AdjPrice!D14-1 -> 0.035050598 | E15: =AdjPrice!E15/AdjPrice!E14-1 -> -0.011577459 | F15: =AdjPrice!F15/AdjPrice!F14-1 -> 0.005453518 | G15: =AdjPrice!G15/AdjPrice!G14-1 -> 0.0015576916 | H15: =AdjPrice!H15/AdjPrice!H14-1 -> 0.063767729 | I15: =SUMPRODUCT(B15:H15, Weights!$B$3:$H$3) -> 0.026322161 | J15: =SUMPRODUCT(B15:H15, Weights!$B$4:$H$4) -> 0.033629654 | K15: =I15-J15 -> -0.0073074928 | L15: =L14*(1+I15) -> 85.950827 | M15: =M14*(1+J15) -> 84.579656 | N15: =MAX(N14,L15) -> 104.03569 | O15: =L15/N15-1 -> -0.17383324 | P15: =MAX(P14,M15) -> 103.77545 | Q15: =M15/P15-1 -> -0.18497429
A16: =AdjPrice!A16 -> 44866 | B16: =AdjPrice!B16/AdjPrice!B15-1 -> 0.051692938 | C16: =AdjPrice!C16/AdjPrice!C15-1 -> 0.13036139 | D16: =AdjPrice!D16/AdjPrice!D15-1 -> 0.061460653 | E16: =AdjPrice!E16/AdjPrice!E15-1 -> 0.036659011 | F16: =AdjPrice!F16/AdjPrice!F15-1 -> 0.024307287 | G16: =AdjPrice!G16/AdjPrice!G15-1 -> 0.0033900988 | H16: =AdjPrice!H16/AdjPrice!H15-1 -> 0.08282695 | I16: =SUMPRODUCT(B16:H16, Weights!$B$3:$H$3) -> 0.053436809 | J16: =SUMPRODUCT(B16:H16, Weights!$B$4:$H$4) -> 0.064359774 | K16: =I16-J16 -> -0.010922965 | L16: =L15*(1+I16) -> 90.543765 | M16: =M15*(1+J16) -> 90.023184 | N16: =MAX(N15,L16) -> 104.03569 | O16: =L16/N16-1 -> -0.12968552 | P16: =MAX(P15,M16) -> 103.77545 | Q16: =M16/P16-1 -> -0.13251942
A17: =AdjPrice!A17 -> 44896 | B17: =AdjPrice!B17/AdjPrice!B16-1 -> -0.058552458 | C17: =AdjPrice!C17/AdjPrice!C16-1 -> -0.021447962 | D17: =AdjPrice!D17/AdjPrice!D16-1 -> -0.050343557 | E17: =AdjPrice!E17/AdjPrice!E16-1 -> -0.0080603213 | F17: =AdjPrice!F17/AdjPrice!F16-1 -> -0.027490646 | G17: =AdjPrice!G17/AdjPrice!G16-1 -> 0.003858151 | H17: =AdjPrice!H17/AdjPrice!H16-1 -> -0.044373976 | I17: =SUMPRODUCT(B17:H17, Weights!$B$3:$H$3) -> -0.02923845 | J17: =SUMPRODUCT(B17:H17, Weights!$B$4:$H$4) -> -0.029848514 | K17: =I17-J17 -> 0.00061006351 | L17: =L16*(1+I17) -> 87.896405 | M17: =M16*(1+J17) -> 87.336125 | N17: =MAX(N16,L17) -> 104.03569 | O17: =L17/N17-1 -> -0.15513217 | P17: =MAX(P16,M17) -> 103.77545 | Q17: =M17/P17-1 -> -0.15841242
A18: =AdjPrice!A18 -> 44927 | B18: =AdjPrice!B18/AdjPrice!B17-1 -> 0.069250508 | C18: =AdjPrice!C18/AdjPrice!C17-1 -> 0.086813379 | D18: =AdjPrice!D18/AdjPrice!D17-1 -> 0.10402521 | E18: =AdjPrice!E18/AdjPrice!E17-1 -> 0.033129159 | F18: =AdjPrice!F18/AdjPrice!F17-1 -> 0.023613454 | G18: =AdjPrice!G18/AdjPrice!G17-1 -> 0.0032750542 | H18: =AdjPrice!H18/AdjPrice!H17-1 -> 0.076459263 | I18: =SUMPRODUCT(B18:H18, Weights!$B$3:$H$3) -> 0.054381674 | J18: =SUMPRODUCT(B18:H18, Weights!$B$4:$H$4) -> 0.059127221 | K18: =I18-J18 -> -0.0047455474 | L18: =L17*(1+I18) -> 92.676359 | M18: =M17*(1+J18) -> 92.500068 | N18: =MAX(N17,L18) -> 104.03569 | O18: =L18/N18-1 -> -0.10918684 | P18: =MAX(P17,M18) -> 103.77545 | Q18: =M18/P18-1 -> -0.10865169
A19: =AdjPrice!A19 -> 44958 | B19: =AdjPrice!B19/AdjPrice!B18-1 -> -0.024018098 | C19: =AdjPrice!C19/AdjPrice!C18-1 -> -0.042696846 | D19: =AdjPrice!D19/AdjPrice!D18-1 -> -0.058642469 | E19: =AdjPrice!E19/AdjPrice!E18-1 -> -0.026659723 | F19: =AdjPrice!F19/AdjPrice!F18-1 -> -0.014993551 | G19: =AdjPrice!G19/AdjPrice!G18-1 -> 0.0029114459 | H19: =AdjPrice!H19/AdjPrice!H18-1 -> -0.031795903 | I19: =SUMPRODUCT(B19:H19, Weights!$B$3:$H$3) -> -0.028374676 | J19: =SUMPRODUCT(B19:H19, Weights!$B$4:$H$4) -> -0.029741431 | K19: =I19-J19 -> 0.0013667556 | L19: =L18*(1+I19) -> 90.046697 | M19: =M18*(1+J19) -> 89.748983 | N19: =MAX(N18,L19) -> 104.03569 | O19: =L19/N19-1 -> -0.13446338 | P19: =MAX(P18,M19) -> 103.77545 | Q19: =M19/P19-1 -> -0.13516166
A20: =AdjPrice!A20 -> 44986 | B20: =AdjPrice!B20/AdjPrice!B19-1 -> 0.027071181 | C20: =AdjPrice!C20/AdjPrice!C19-1 -> 0.028395361 | D20: =AdjPrice!D20/AdjPrice!D19-1 -> -0.021554732 | E20: =AdjPrice!E20/AdjPrice!E19-1 -> 0.026756924 | F20: =AdjPrice!F20/AdjPrice!F19-1 -> 0.02555514 | G20: =AdjPrice!G20/AdjPrice!G19-1 -> 0.0050939865 | H20: =AdjPrice!H20/AdjPrice!H19-1 -> 0.028501934 | I20: =SUMPRODUCT(B20:H20, Weights!$B$3:$H$3) -> 0.020986674 | J20: =SUMPRODUCT(B20:H20, Weights!$B$4:$H$4) -> 0.02780393 | K20: =I20-J20 -> -0.006817256 | L20: =L19*(1+I20) -> 91.936478 | M20: =M19*(1+J20) -> 92.244358 | N20: =MAX(N19,L20) -> 104.03569 | O20: =L20/N20-1 -> -0.11629864 | P20: =MAX(P19,M20) -> 103.77545 | Q20: =M20/P20-1 -> -0.11111576
A21: =AdjPrice!A21 -> 45017 | B21: =AdjPrice!B21/AdjPrice!B20-1 -> 0.010779 | C21: =AdjPrice!C21/AdjPrice!C20-1 -> 0.018837237 | D21: =AdjPrice!D21/AdjPrice!D20-1 -> 0.0031311449 | E21: =AdjPrice!E21/AdjPrice!E20-1 -> 0.0058793231 | F21: =AdjPrice!F21/AdjPrice!F20-1 -> 0.0020879379 | G21: =AdjPrice!G21/AdjPrice!G20-1 -> 0.0030965986 | H21: =AdjPrice!H21/AdjPrice!H20-1 -> 0.01422553 | I21: =SUMPRODUCT(B21:H21, Weights!$B$3:$H$3) -> 0.0080652675 | J21: =SUMPRODUCT(B21:H21, Weights!$B$4:$H$4) -> 0.010887047 | K21: =I21-J21 -> -0.0028217798 | L21: =L20*(1+I21) -> 92.67797 | M21: =M20*(1+J21) -> 93.248627 | N21: =MAX(N20,L21) -> 104.03569 | O21: =L21/N21-1 -> -0.10917135 | P21: =MAX(P20,M21) -> 103.77545 | Q21: =M21/P21-1 -> -0.10143843
A22: =AdjPrice!A22 -> 45047 | B22: =AdjPrice!B22/AdjPrice!B21-1 -> 0.004265404 | C22: =AdjPrice!C22/AdjPrice!C21-1 -> -0.035022251 | D22: =AdjPrice!D22/AdjPrice!D21-1 -> -0.039616071 | E22: =AdjPrice!E22/AdjPrice!E21-1 -> -0.01163762 | F22: =AdjPrice!F22/AdjPrice!F21-1 -> 0.0014324946 | G22: =AdjPrice!G22/AdjPrice!G21-1 -> 0.0032531627 | H22: =AdjPrice!H22/AdjPrice!H21-1 -> -0.012098819 | I22: =SUMPRODUCT(B22:H22, Weights!$B$3:$H$3) -> -0.011262348 | J22: =SUMPRODUCT(B22:H22, Weights!$B$4:$H$4) -> -0.01191434 | K22: =I22-J22 -> 0.00065199203 | L22: =L21*(1+I22) -> 91.634199 | M22: =M21*(1+J22) -> 92.137631 | N22: =MAX(N21,L22) -> 104.03569 | O22: =L22/N22-1 -> -0.11920418 | P22: =MAX(P21,M22) -> 103.77545 | Q22: =M22/P22-1 -> -0.1121442
A23: =AdjPrice!A23 -> 45078 | B23: =AdjPrice!B23/AdjPrice!B22-1 -> 0.067287089 | C23: =AdjPrice!C23/AdjPrice!C22-1 -> 0.044362583 | D23: =AdjPrice!D23/AdjPrice!D22-1 -> 0.056294592 | E23: =AdjPrice!E23/AdjPrice!E22-1 -> -0.0022371691 | F23: =AdjPrice!F23/AdjPrice!F22-1 -> 6.0873853e-05 | G23: =AdjPrice!G23/AdjPrice!G22-1 -> 0.0047482368 | H23: =AdjPrice!H23/AdjPrice!H22-1 -> 0.058079767 | I23: =SUMPRODUCT(B23:H23, Weights!$B$3:$H$3) -> 0.028681011 | J23: =SUMPRODUCT(B23:H23, Weights!$B$4:$H$4) -> 0.033952993 | K23: =I23-J23 -> -0.0052719816 | L23: =L22*(1+I23) -> 94.26236 | M23: =M22*(1+J23) -> 95.265979 | N23: =MAX(N22,L23) -> 104.03569 | O23: =L23/N23-1 -> -0.09394206 | P23: =MAX(P22,M23) -> 103.77545 | Q23: =M23/P23-1 -> -0.081998839
A24: =AdjPrice!A24 -> 45108 | B24: =AdjPrice!B24/AdjPrice!B23-1 -> 0.036635471 | C24: =AdjPrice!C24/AdjPrice!C23-1 -> 0.0388731 | D24: =AdjPrice!D24/AdjPrice!D23-1 -> 0.020344749 | E24: =AdjPrice!E24/AdjPrice!E23-1 -> -0.001186074 | F24: =AdjPrice!F24/AdjPrice!F23-1 -> -0.001270079 | G24: =AdjPrice!G24/AdjPrice!G23-1 -> 0.0038363139 | H24: =AdjPrice!H24/AdjPrice!H23-1 -> 0.037224109 | I24: =SUMPRODUCT(B24:H24, Weights!$B$3:$H$3) -> 0.016669789 | J24: =SUMPRODUCT(B24:H24, Weights!$B$4:$H$4) -> 0.021860036 | K24: =I24-J24 -> -0.0051902463 | L24: =L23*(1+I24) -> 95.833694 | M24: =M23*(1+J24) -> 97.348497 | N24: =MAX(N23,L24) -> 104.03569 | O24: =L24/N24-1 -> -0.078838266 | P24: =MAX(P23,M24) -> 103.77545 | Q24: =M24/P24-1 -> -0.061931301
A25: =AdjPrice!A25 -> 45139 | B25: =AdjPrice!B25/AdjPrice!B24-1 -> -0.019312645 | C25: =AdjPrice!C25/AdjPrice!C24-1 -> -0.043940991 | D25: =AdjPrice!D25/AdjPrice!D24-1 -> -0.033779056 | E25: =AdjPrice!E25/AdjPrice!E24-1 -> -0.0066038311 | F25: =AdjPrice!F25/AdjPrice!F24-1 -> 0.0020961992 | G25: =AdjPrice!G25/AdjPrice!G24-1 -> 0.0047920161 | H25: =AdjPrice!H25/AdjPrice!H24-1 -> -0.028432213 | I25: =SUMPRODUCT(B25:H25, Weights!$B$3:$H$3) -> -0.016224334 | J25: =SUMPRODUCT(B25:H25, Weights!$B$4:$H$4) -> -0.01970086 | K25: =I25-J25 -> 0.0034765258 | L25: =L24*(1+I25) -> 94.278856 | M25: =M24*(1+J25) -> 95.430648 | N25: =MAX(N24,L25) -> 104.03569 | O25: =L25/N25-1 -> -0.093783501 | P25: =MAX(P24,M25) -> 103.77545 | Q25: =M25/P25-1 -> -0.080412061
A26: =AdjPrice!A26 -> 45170 | B26: =AdjPrice!B26/AdjPrice!B25-1 -> -0.04801079 | C26: =AdjPrice!C26/AdjPrice!C25-1 -> -0.034019213 | D26: =AdjPrice!D26/AdjPrice!D25-1 -> -0.072637695 | E26: =AdjPrice!E26/AdjPrice!E25-1 -> -0.024792768 | F26: =AdjPrice!F26/AdjPrice!F25-1 -> -0.01748136 | G26: =AdjPrice!G26/AdjPrice!G25-1 -> 0.0039166646 | H26: =AdjPrice!H26/AdjPrice!H25-1 -> -0.042547891 | I26: =SUMPRODUCT(B26:H26, Weights!$B$3:$H$3) -> -0.03423355 | J26: =SUMPRODUCT(B26:H26, Weights!$B$4:$H$4) -> -0.035445842 | K26: =I26-J26 -> 0.0012122919 | L26: =L25*(1+I26) -> 91.051356 | M26: =M25*(1+J26) -> 92.048028 | N26: =MAX(N25,L26) -> 104.03569 | O26: =L26/N26-1 -> -0.12480651 | P26: =MAX(P25,M26) -> 103.77545 | Q26: =M26/P26-1 -> -0.11300763
... A62: =AdjPrice!A62 -> 46266 | B62: =AdjPrice!B62/AdjPrice!B61-1 -> -0.0051380151 | C62: =AdjPrice!C62/AdjPrice!C61-1 -> -0.018844392 | D62: =AdjPrice!D62/AdjPrice!D61-1 -> -0.053140016 | E62: =AdjPrice!E62/AdjPrice!E61-1 -> -0.024407176 | F62: =AdjPrice!F62/AdjPrice!F61-1 -> -0.011996789 | G62: =AdjPrice!G62/AdjPrice!G61-1 -> 0.0025264501 | H62: =AdjPrice!H62/AdjPrice!H61-1 -> -0.010544607 | I62: =SUMPRODUCT(B62:H62, Weights!$B$3:$H$3) -> -0.018420513 | J62: =SUMPRODUCT(B62:H62, Weights!$B$4:$H$4) -> -0.016089635 | K62: =I62-J62 -> -0.0023308779 | L62: =L61*(1+I62) -> 126.83047 | M62: =M61*(1+J62) -> 137.81201 | N62: =MAX(N61,L62) -> 129.21059 | O62: =L62/N62-1 -> -0.018420513 | P62: =MAX(P61,M62) -> 140.06561 | Q62: =M62/P62-1 -> -0.016089635

Sheet Metrics
A1: Performance and Risk Metrics
A3: Risk-Free Rate (annual) | B3: 0.03
B5: Portfolio | C5: Portfolio | D5: Portfolio | E5: Benchmark | F5: Benchmark | G5: Benchmark
A6: Periods | B6: 1Y | C6: 3Y | D6: 5Y | E6: 1Y | F6: 3Y | G6: 5Y
A7: Months | B7: 12 | C7: 36 | D7: 60 | E7: 12 | F7: 36 | G7: 60
A8: Cumulative Returns | B8: {=Calc!$L$62/INDEX(Calc!$L$2:$L$62,ROWS(Calc!$L$2:$L$62)-B$7)-1} -> 0.065347825 | C8: {=Calc!$L$62/INDEX(Calc!$L$2:$L$62,ROWS(Calc!$L$2:$L$62)-C$7)-1} -> 0.39295527 | D8: {=Calc!$L$62/INDEX(Calc!$L$2:$L$62,ROWS(Calc!$L$2:$L$62)-D$7)-1} -> 0.26830466 | E8: {=Calc!$M$62/INDEX(Calc!$M$2:$M$62,ROWS(Calc!$M$2:ML$62)-B$7)-1} -> 0.092320088 | F8: {=Calc!$M$62/INDEX(Calc!$M$2:$M$62,ROWS(Calc!$M$2:MM$62)-C$7)-1} -> 0.49717501 | G8: {=Calc!$M$62/INDEX(Calc!$M$2:$M$62,ROWS(Calc!$M$2:MN$62)-D$7)-1} -> 0.37812007
A9: Annualised Returns | B9: =(1+B8)^(12/B$7)-1 -> 0.065347825 | C9: =(1+C8)^(12/C$7)-1 -> 0.11680939 | D9: =(1+D8)^(12/D$7)-1 -> 0.048684183 | E9: =(1+E8)^(12/E$7)-1 -> 0.092320088 | F9: =(1+F8)^(12/F$7)-1 -> 0.14399517 | G9: =(1+G8)^(12/G$7)-1 -> 0.066245992
A10: Volatility | B10: =_xlfn.STDEV.S(INDEX(Calc!$I$3:$I$62,ROWS(Calc!$I$3:$I$62)-B$7+1):'Calc'!$I$62)*SQRT(12) -> 0.073806488 | C10: =_xlfn.STDEV.S(INDEX(Calc!$I$3:$I$62,ROWS(Calc!$I$3:$I$62)-C$7+1):'Calc'!$I$62)*SQRT(12) -> 0.077418426 | D10: =_xlfn.STDEV.S(INDEX(Calc!$I$3:$I$62,ROWS(Calc!$I$3:$I$62)-D$7+1):'Calc'!$I$62)*SQRT(12) -> 0.098145805 | E10: =_xlfn.STDEV.S(INDEX(Calc!$J$3:$J$62,ROWS(Calc!$J$3:$J$62)-B$7+1):'Calc'!$J$62)*SQRT(12) -> 0.086607725 | F10: =_xlfn.STDEV.S(INDEX(Calc!$J$3:$J$62,ROWS(Calc!$J$3:$J$62)-C$7+1):'Calc'!$J$62)*SQRT(12) -> 0.085429348 | G10: =_xlfn.STDEV.S(INDEX(Calc!$J$3:$J$62,ROWS(Calc!$J$3:$J$62)-D$7+1):'Calc'!$J$62)*SQRT(12) -> 0.1094657
A11: Sharpe Ratio | B11: =(B9-$B$3)/B10 -> 0.47892571 | C11: =(C9-$B$3)/C10 -> 1.1213014 | D11: =(D9-$B$3)/D10 -> 0.19037169 | E11: =(E9-$B$3)/E10 -> 0.71956732 | F11: =(F9-$B$3)/F10 -> 1.3343795 | G11: =(G9-$B$3)/G10 -> 0.33111735
A12: Excess Returns (annual) | B12: =B9-E9 -> -0.026972263 | C12: =C9-F9 -> -0.027185777 | D12: =D9-G9 -> -0.017561809
A13: Tracking Error | B13: =_xlfn.STDEV.S(INDEX(Calc!$K$3:$K$62,ROWS(Calc!$K$3:$K$62)-B$7+1):'Calc'!$K$62)*SQRT(12) -> 0.01881344 | C13: =_xlfn.STDEV.S(INDEX(Calc!$K$3:$K$62,ROWS(Calc!$K$3:$K$62)-C$7+1):'Calc'!$K$62)*SQRT(12) -> 0.015712393 | D13: =_xlfn.STDEV.S(INDEX(Calc!$K$3:$K$62,ROWS(Calc!$K$3:$K$62)-D$7+1):'Calc'!$K$62)*SQRT(12) -> 0.016889131
A14: Information Ratio | B14: =B12/B13 -> -1.4336699 | C14: =C12/C13 -> -1.7302124 | D14: =D12/D13 -> -1.0398291
A15: Max Drawdown | B15: =MIN(Calc!$O$2:$O$62) -> -0.195022 | C15: =MIN(Calc!$O$2:$O$62) -> -0.195022 | D15: =MIN(Calc!$O$2:$O$62) -> -0.195022 | G15: =MIN(Calc!$Q$2:$Q$62) -> -0.21149155
A18: Name | B18: Risk (vol) | C18: Return (ann.)
A19: VTI | B19: =_xlfn.STDEV.S(Calc!B3:B62)*SQRT(12) -> 0.15931096 | C19: =(AdjPrice!B62/AdjPrice!B2)^(12/(ROWS(AdjPrice!B2:B62)-1))-1 -> 0.12617985
A20: VXUS | B20: =_xlfn.STDEV.S(Calc!C3:C62)*SQRT(12) -> 0.15139007 | C20: =(AdjPrice!C62/AdjPrice!C2)^(12/(ROWS(AdjPrice!C2:C62)-1))-1 -> 0.095149995
A21: VNQ | B21: =_xlfn.STDEV.S(Calc!D3:D62)*SQRT(12) -> 0.19130698 | C21: =(AdjPrice!D62/AdjPrice!D2)^(12/(ROWS(AdjPrice!D2:D62)-1))-1 -> 0.015617473
A22: BND | B22: =_xlfn.STDEV.S(Calc!E3:E62)*SQRT(12) -> 0.064461537 | C22: =(AdjPrice!E62/AdjPrice!E2)^(12/(ROWS(AdjPrice!E2:E62)-1))-1 -> -0.0060312968
A23: BNDX | B23: =_xlfn.STDEV.S(Calc!F3:F62)*SQRT(12) -> 0.053424772 | C23: =(AdjPrice!F62/AdjPrice!F2)^(12/(ROWS(AdjPrice!F2:F62)-1))-1 -> -0.00048511884
A24: SHV | B24: =_xlfn.STDEV.S(Calc!G3:G62)*SQRT(12) -> 0.005704352 | C24: =(AdjPrice!G62/AdjPrice!G2)^(12/(ROWS(AdjPrice!G2:G62)-1))-1 -> 0.035524034
A25: VTI | B25: =_xlfn.STDEV.S(Calc!H3:H62)*SQRT(12) -> 0.14905733 | C25: =(AdjPrice!H62/AdjPrice!H2)^(12/(ROWS(AdjPrice!H2:H62)-1))-1 -> 0.11436061
A26: Portfolio | B26: =Metrics!D10 -> 0.098145805 | C26: =Metrics!D9 -> 0.048684183
A27: Benchmark | B27: =Metrics!G10 -> 0.1094657 | C27: =Metrics!G9 -> 0.066245992

Sheet Attribution
Q1: Master Check
H2: Allocation | I2: Selection | J2: Interaction | K2: Total | L2: Actual Excess | Q2: =IF(COUNTIF(O10:O69,"FAIL")=0,"PASS","FAIL") -> PASS
A3: Class | B3: Equity | C3: Property | D3: Bonds | E3: Cash | G3: Last 12M | H3: =SUM(J58:J69) -> -0.028218615 | I3: =SUM(K58:K69) -> 0.0024174938 | J3: =SUM(L58:L69) -> -0.00029171787 | K3: =SUM(H3:J3) -> -0.026092839 | L3: =SUM(N58:N69) -> -0.026092839
A4: Portfolio Weight | B4: =Weights!B3+Weights!C3+Weights!H3 -> 0.4 | C4: =Weights!D3 -> 0.1 | D4: =Weights!E3+Weights!F3 -> 0.45 | E4: =Weights!G3 -> 0.05 | G4: Full Period | H4: =SUM(J10:J69) -> -0.095224565 | I4: =SUM(K10:K69) -> 0.0067370522 | J4: =SUM(L10:L69) -> -0.0007413468 | K4: =SUM(H4:J4) -> -0.089228859 | L4: =SUM(N10:N69) -> -0.089228859
A5: Benchmark Weight | B5: =Weights!B4+Weights!C4+Weights!H4 -> 0.6 | C5: =Weights!D4 -> 0 | D5: =Weights!E4+Weights!F4 -> 0.4 | E5: =Weights!G4 -> 0
R7: =SUM(M10:M69)-SUM(N10:N69) -> 0
A9: Date | B9: Port Equity | C9: Port Property | D9: Port Bonds | E9: Port Cash | F9: Bench Equity | G9: Bench Property | H9: Bench Bonds | I9: Bench Cash | J9: Allocation | K9: Selection | L9: Interaction | M9: Total Effect | N9: Actual Excess | O9: Tie-Out
A10: =Calc!A3 -> 44470 | B10: =(Calc!B3*Weights!$B$3+Calc!C3*Weights!$C$3+Calc!H3*Weights!$H$3)/$B$4 -> 0.052584895 | C10: =Calc!D3 -> 0.071330248 | D10: =(Calc!E3*Weights!$E$3+Calc!F3*Weights!$F$3)/$D$4 -> -0.0010069759 | E10: =Calc!G3 -> -0.00027109759 | F10: =Calc!H3 -> 0.051458313 | G10: =Calc!D3 -> 0.071330248 | H10: =Calc!E3 -> 0.00070307377 | I10: =Calc!G3 -> -0.00027109759 | J10: {=SUMPRODUCT($B$4:$E$4-$B$5:$E$5,F10:I10-Calc!J3)} -> -0.003137039 | K10: {=SUMPRODUCT($B$5:$E$5,B10:E10-F10:I10)} -> -8.0708167e-06 | L10: {=SUMPRODUCT($B$4:$E$4-$B$5:$E$5,B10:E10-F10:I10)} -> -0.00031081882 | M10: =J10+K10+L10 -> -0.0034559287 | N10: =Calc!K3 -> -0.0034559287 | O10: =IF(ABS(M10-N10)<0.000001,"PASS","FAIL") -> PASS
A11: =Calc!A4 -> 44501 | B11: =(Calc!B4*Weights!$B$3+Calc!C4*Weights!$C$3+Calc!H4*Weights!$H$3)/$B$4 -> -0.025089143 | C11: =Calc!D4 -> -0.021093216 | D11: =(Calc!E4*Weights!$E$3+Calc!F4*Weights!$F$3)/$D$4 -> 0.0048865246 | E11: =Calc!G4 -> -0.00045297056 | F11: =Calc!H4 -> -0.026151164 | G11: =Calc!D4 -> -0.021093216 | H11: =Calc!E4 -> 0.0020412549 | I11: =Calc!G4 -> -0.00045297056 | J11: {=SUMPRODUCT($B$4:$E$4-$B$5:$E$5,F11:I11-Calc!J4)} -> 0.0032003255 | K11: {=SUMPRODUCT($B$5:$E$5,B11:E11-F11:I11)} -> 0.0017753207 | L11: {=SUMPRODUCT($B$4:$E$4-$B$5:$E$5,B11:E11-F11:I11)} -> -7.0140784e-05 | M11: =J11+K11+L11 -> 0.0049055055 | N11: =Calc!K4 -> 0.0049055055 | O11: =IF(ABS(M11-N11)<0.000001,"PASS","FAIL") -> PASS
A12: =Calc!A5 -> 44531 | B12: =(Calc!B5*Weights!$B$3+Calc!C5*Weights!$C$3+Calc!H5*Weights!$H$3)/$B$4 -> 0.037102798 | C12: =Calc!D5 -> 0.097055857 | D12: =(Calc!E5*Weights!$E$3+Calc!F5*Weights!$F$3)/$D$4 -> -0.004559535 | E12: =Calc!G5 -> 0.00027195508 | F12: =Calc!H5 -> 0.038059249 | G12: =Calc!D5 -> 0.097055857 | H12: =Calc!E5 -> -0.003103218 | I12: =Calc!G5 -> 0.00027195508 | J12: {=SUMPRODUCT($B$4:$E$4-$B$5:$E$5,F12:I12-Calc!J5)} -> 0.0019521726 | K12: {=SUMPRODUCT($B$5:$E$5,B12:E12-F12:I12)} -> -0.0011563978 | L12: {=SUMPRODUCT($B$4:$E$4-$B$5:$E$5,B12:E12-F12:I12)} -> 0.00011847446 | M12: =J12+K12+L12 -> 0.00091424933 | N12: =Calc!K5 -> 0.00091424933 | O12: =IF(ABS(M12-N12)<0.000001,"PASS","FAIL") -> PASS
A13: =Calc!A6 -> 44562 | B13: =(Calc!B6*Weights!$B$3+Calc!C6*Weights!$C$3+Calc!H6*Weights!$H$3)/$B$4 -> -0.048489877 | C13: =Calc!D6 -> -0.084216774 | D13: =(Calc!E6*Weights!$E$3+Calc!F6*Weights!$F$3)/$D$4 -> -0.018358699 | E13: =Calc!G6 -> -0.00081498253 | F13: =Calc!H6 -> -0.045797119 | G13: =Calc!D6 -> -0.084216774 | H13: =Calc!E6 -> -0.020648965 | I13: =Calc!G6 -> -0.00081498253 | J13: {=SUMPRODUCT($B$4:$E$4-$B$5:$E$5,F13:I13-Calc!J6)} -> -0.00033545093 | K13: {=SUMPRODUCT($B$5:$E$5,B13:E13-F13:I13)} -> -0.00069954813 | L13: {=SUMPRODUCT($B$4:$E$4-$B$5:$E$5,B13:E13-F13:I13)} -> 0.00065306475 | M13: =J13+K13+L13 -> -0.0003819343 | N13: =Calc!K6 -> -0.0003819343 | O13: =IF(ABS(M13-N13)<0.000001,"PASS","FAIL") -> PASS
A14: =Calc!A7 -> 44593 | B14: =(Calc!B7*Weights!$B$3+Calc!C7*Weights!$C$3+Calc!H7*Weights!$H$3)/$B$4 -> -0.026226467 | C14: =Calc!D7 -> -0.034826873 | D14: =(Calc!E7*Weights!$E$3+Calc!F7*Weights!$F$3)/$D$4 -> -0.0117759 | E14: =Calc!G7 -> -0.00036272119 | F14: =Calc!H7 -> -0.027704748 | G14: =Calc!D7 -> -0.034826873 | H14: =Calc!E7 -> -0.011380687 | I14: =Calc!G7 -> -0.00036272119 | J14: {=SUMPRODUCT($B$4:$E$4-$B$5:$E$5,F14:I14-Calc!J7)} -> 0.0014710919 | K14: {=SUMPRODUCT($B$5:$E$5,B14:E14-F14:I14)} -> 0.00072888342 | L14: {=SUMPRODUCT($B$4:$E$4-$B$5:$E$5,B14:E14-F14:I14)} -> -0.00031541685 | M14: =J14+K14+L14 -> 0.0018845585 | N14: =Calc!K7 -> 0.0018845585 | O14: =IF(ABS(M14-N14)<0.000001,"PASS","FAIL") -> PASS
A15: =Calc!A8 -> 44621 | B15: =(Calc!B8*Weights!$B$3+Calc!C8*Weights!$C$3+Calc!H8*Weights!$H$3)/$B$4 -> 0.01931054 | C15: =Calc!D8 -> 0.062639438 | D15: =(Calc!E8*Weights!$E$3+Calc!F8*Weights!$F$3)/$D$4 -> -0.025774063 | E15: =Calc!G8 -> -0.00036277009 | F15: =Calc!H8 -> 0.018854205 | G15: =Calc!D8 -> 0.062639438 | H15: =Calc!E8 -> -0.027521085 | I15: =Calc!G8 -> -0.00036277009 | J15: {=SUMPRODUCT($B$4:$E$4-$B$5:$E$5,F15:I15-Calc!J8)} -> 0.0010989099 | K15: {=SUMPRODUCT($B$5:$E$5,B15:E15-F15:I15)} -> 0.0009726097 | L15: {=SUMPRODUCT($B$4:$E$4-$B$5:$E$5,B15:E15-F15:I15)} -> -3.9157999e-06 | M15: =J15+K15+L15 -> 0.0020676038 | N15: =Calc!K8 -> 0.0020676038 | O15: =IF(ABS(M15-N15)<0.000001,"PASS","FAIL") -> PASS
A16: =Calc!A9 -> 44652 | B16: =(Calc!B9*Weights!$B$3+Calc!C9*Weights!$C$3+Calc!H9*Weights!$H$3)/$B$4 -> -0.081428187 | C16: =Calc!D9 -> -0.040878693 | D16: =(Calc!E9*Weights!$E$3+Calc!F9*Weights!$F$3)/$D$4 -> -0.036484088 | E16: =Calc!G9 -> -0.00029066891 | F16: =Calc!H9 -> -0.080955758 | G16: =Calc!D9 -> -0.040878693 | H16: =Calc!E9 -> -0.039726774 | I16: =Calc!G9 -> -0.00029066891 | J16: {=SUMPRODUCT($B$4:$E$4-$B$5:$E$5,F16:I16-Calc!J9)} -> 0.01010241 | K16: {=SUMPRODUCT($B$5:$E$5,B16:E16-F16:I16)} -> 0.0010136174 | L16: {=SUMPRODUCT($B$4:$E$4-$B$5:$E$5,B16:E16-F16:I16)} -> 0.00025662002 | M16: =J16+K16+L16 -> 0.011372648 | N16: =Calc!K9 -> 0.011372648 | O16: =IF(ABS(M16-N16)<0.000001,"PASS","FAIL") -> PASS
A17: =Calc!A10 -> 44682 | B17: =(Calc!B10*Weights!$B$3+Calc!C10*Weights!$C$3+Calc!H10*Weights!$H$3)/$B$4 -> 0.0041350493 | C17: =Calc!D10 -> -0.046854052 | D17: =(Calc!E10*Weights!$E$3+Calc!F10*Weights!$F$3)/$D$4 -> 0.0032870888 | E17: =Calc!G10 -> 0.00066303036 | F17: =Calc!H10 -> 0.0049418198 | G17: =Calc!D10 -> -0.046854052 | H17: =Calc!E10 -> 0.0082972047 | I17: =Calc!G10 -> 0.00066303036 | J17: {=SUMPRODUCT($B$4:$E$4-$B$5:$E$5,F17:I17-Calc!J10)} -> -0.0052257574 | K17: {=SUMPRODUCT($B$5:$E$5,B17:E17-F17:I17)} -> -0.0024881087 | L17: {=SUMPRODUCT($B$4:$E$4-$B$5:$E$5,B17:E17-F17:I17)} -> -8.9151699e-05 | M17: =J17+K17+L17 -> -0.0078030177 | N17: =Calc!K10 -> -0.0078030177 | O17: =IF(ABS(M17-N17)<0.000001,"PASS","FAIL") -> PASS
A18: =Calc!A11 -> 44713 | B18: =(Calc!B11*Weights!$B$3+Calc!C11*Weights!$C$3+Calc!H11*Weights!$H$3)/$B$4 -> -0.081215861 | C18: =Calc!D11 -> -0.074488786 | D18: =(Calc!E11*Weights!$E$3+Calc!F11*Weights!$F$3)/$D$4 -> -0.01682019 | E18: =Calc!G11 -> -0.00075332408 | F18: =Calc!H11 -> -0.081217382 | G18: =Calc!D11 -> -0.074488786 | H18: =Calc!E11 -> -0.016620347 | I18: =Calc!G11 -> -0.00075332408 | J18: {=SUMPRODUCT($B$4:$E$4-$B$5:$E$5,F18:I18-Calc!J11)} -> 0.0079259143 | K18: {=SUMPRODUCT($B$5:$E$5,B18:E18-F18:I18)} -> -7.902394e-05 | L18: {=SUMPRODUCT($B$4:$E$4-$B$5:$E$5,B18:E18-F18:I18)} -> -1.0296517e-05 | M18: =J18+K18+L18 -> 0.0078365938 | N18: =Calc!K11 -> 0.0078365938 | O18: =IF(ABS(M18-N18)<0.000001,"PASS","FAIL") -> PASS
A19: =Calc!A12 -> 44743 | B19: =(Calc!B12*Weights!$B$3+Calc!C12*Weights!$C$3+Calc!H12*Weights!$H$3)/$B$4 -> 0.072078099 | C19: =Calc!D12 -> 0.086159705 | D19: =(Calc!E12*Weights!$E$3+Calc!F12*Weights!$F$3)/$D$4 -> 0.026606783 | E19: =Calc!G12 -> 0.00088160998 | F19: =Calc!H12 -> 0.069837952 | G19: =Calc!D12 -> 0.086159705 | H19: =Calc!E12 -> 0.023818233 | I19: =Calc!G12 -> 0.00088160998 | J19: {=SUMPRODUCT($B$4:$E$4-$B$5:$E$5,F19:I19-Calc!J12)} -> -0.0041166277 | K19: {=SUMPRODUCT($B$5:$E$5,B19:E19-F19:I19)} -> 0.0024595088 | L19: {=SUMPRODUCT($B$4:$E$4-$B$5:$E$5,B19:E19-F19:I19)} -> -0.00030860197 | M19: =J19+K19+L19 -> -0.0019657209 | N19: =Calc!K12 -> -0.0019657209 | O19: =IF(ABS(M19-N19)<0.000001,"PASS","FAIL") -> PASS
A20: =Calc!A13 -> 44774 | B20: =(Calc!B13*Weights!$B$3+Calc!C13*Weights!$C$3+Calc!H13*Weights!$H$3)/$B$4 -> -0.040128922 | C20: =Calc!D13 -> -0.060125224 | D20: =(Calc!E13*Weights!$E$3+Calc!F13*Weights!$F$3)/$D$4 -> -0.030673088 | E20: =Calc!G13 -> 0.0012816784 | F20: =Calc!H13 -> -0.040525495 | G20: =Calc!D13 -> -0.060125224 | H20: =Calc!E13 -> -0.027975095 | I20: =Calc!G13 -> 0.0012816784 | J20: {=SUMPRODUCT($B$4:$E$4-$B$5:$E$5,F20:I20-Calc!J13)} -> 0.00075790577 | K20: {=SUMPRODUCT($B$5:$E$5,B20:E20-F20:I20)} -> -0.0008412536 | L20: {=SUMPRODUCT($B$4:$E$4-$B$5:$E$5,B20:E20-F20:I20)} -> -0.00021421431 | M20: =J20+K20+L20 -> -0.00029756214 | N20: =Calc!K13 -> -0.00029756214 | O20: =IF(ABS(M20-N20)<0.000001,"PASS","FAIL") -> PASS
A21: =Calc!A14 -> 44805 | B21: =(Calc!B14*Weights!$B$3+Calc!C14*Weights!$C$3+Calc!H14*Weights!$H$3)/$B$4 -> -0.094837229 | C21: =Calc!D14 -> -0.12871323 | D21: =(Calc!E14*Weights!$E$3+Calc!F14*Weights!$F$3)/$D$4 -> -0.037530297 | E21: =Calc!G14 -> 0.00028205762 | F21: =Calc!H14 -> -0.095289576 | G21: =Calc!D14 -> -0.12871323 | H21: =Calc!E14 -> -0.041829988 | I21: =Calc!G14 -> 0.00028205762 | J21: {=SUMPRODUCT($B$4:$E$4-$B$5:$E$5,F21:I21-Calc!J14)} -> 0.0041091959 | K21: {=SUMPRODUCT($B$5:$E$5,B21:E21-F21:I21)} -> 0.0019912844 | L21: {=SUMPRODUCT($B$4:$E$4-$B$5:$E$5,B21:E21-F21:I21)} -> 0.00012451523 | M21: =J21+K21+L21 -> 0.0062249956 | N21: =Calc!K14 -> 0.0062249956 | O21: =IF(ABS(M21-N21)<0.000001,"PASS","FAIL") -> PASS
... A69: =Calc!A62 -> 46266 | B69: =(Calc!B62*Weights!$B$3+Calc!C62*Weights!$C$3+Calc!H62*Weights!$H$3)/$B$4 -> -0.010277906 | C69: =Calc!D62 -> -0.053140016 | D69: =(Calc!E62*Weights!$E$3+Calc!F62*Weights!$F$3)/$D$4 -> -0.02027038 | E69: =Calc!G62 -> 0.0025264501 | F69: =Calc!H62 -> -0.010544607 | G69: =Calc!D62 -> -0.053140016 | H69: =Calc!E62 -> -0.024407176 | I69: =Calc!G62 -> 0.0025264501 | J69: {=SUMPRODUCT($B$4:$E$4-$B$5:$E$5,F69:I69-Calc!J62)} -> -0.0042991164 | K69: {=SUMPRODUCT($B$5:$E$5,B69:E69-F69:I69)} -> 0.001814739 | L69: {=SUMPRODUCT($B$4:$E$4-$B$5:$E$5,B69:E69-F69:I69)} -> 0.00015349958 | M69: =J69+K69+L69 -> -0.0023308779 | N69: =Calc!K62 -> -0.0023308779 | O69: =IF(ABS(M69-N69)<0.000001,"PASS","FAIL") -> PASS

Sheet Checks
A1: Model Checks
A2: Report Date | B2: 46266
A3: Overall Status | B3: =IF(COUNTIF(B6:B17,"PASS")=ROWS(B6:B17),"PASS","FAIL") -> PASS
A5: Check | B5: Result
A6: Portfolio Weights sum to 100 | B6: =IF(ABS(Weights!I3-1)<0.0001,"PASS","FAIL") -> PASS
A7: Benchmark Weights sum to 100 | B7: =IF(ABS(Weights!I4-1)<0.0001,"PASS","FAIL") -> PASS
A8: No Negative Weights | B8: =IF(MIN(Weights!B3:H4)>=0,"PASS","FAIL") -> PASS
A9: Risk-free rate is sensible (0% to 15%) | B9: =IF(AND(Metrics!B3>=0,Metrics!B3<=0.15),"PASS","FAIL") -> PASS
A10: Every Price is a number | B10: =IF(COUNT(AdjPrice!B2:H62)=ROWS(AdjPrice!B2:H62)*COLUMNS(AdjPrice!B2:H62),"PASS","FAIL") -> PASS
A11: Date runs oldest to newest | B11: {=IF(SUMPRODUCT(--(AdjPrice!A3:A62<=AdjPrice!A2:A61))=0,"PASS","FAIL")} -> PASS
A12: No missing months | B12: {=IF(SUMPRODUCT(--(AdjPrice!A3:A62-AdjPrice!A2:A61>35))=0,"PASS","FAIL")} -> PASS
A13: No implausible monthy returns | B13: =IF(COUNTIF(Calc!B3:H62,">0.25")+COUNTIF(Calc!B3:H62,"<-0.25")=0,"PASS","REVIEW") -> PASS
A14: Latest data matches report date | B14: =IF(AND(YEAR(AdjPrice!A62)=YEAR(B2),MONTH(AdjPrice!A62)=MONTH(B2)),"PASS","FAIL") -> PASS
A15: No error values in calc | B15: {=IF(SUMPRODUCT(--ISERROR(Calc!B3:M62))=0,"PASS","FAIL")} -> PASS
A16: Index ties to compounded returns | B16: {=IF(AND(ABS(Calc!L62/Calc!L2-EXP(SUMPRODUCT(LN(1+Calc!I3:I62))))<0.000001,ABS(Calc!M62/Calc!M2-EXP(SUMPRODUCT(LN(1+Calc!J3:J62))))<0.000001),"PASS","FAIL")} -> PASS
A17: Attribution ties to actual excess return | B17: =IF(AND(Attribution!Q2="PASS",ABS(Attribution!K4-Attribution!L4)<0.000001),"PASS","FAIL") -> PASS

Sheet Dashboard
A1: Portfolio Performance Report | L1: Checks: | M1: =Checks!B3 -> PASS
A2: ="Data to "&TEXT(Calc!A62,"mmmm yyyy")&" | Benchmark: 60% VT / 40% BND | Total return, monthly rebalanced" -> Data to September 2026 | Benchmark: 60% VT / 40% BND | Total return, monthly rebalanced
B4: Portfolio | E4: Benchmark | J4: Allocation | K4: Selection | L4: Interaction
B5: 1Y | C5: 3Y | D5: 5Y | E5: 1Y | F5: 3Y | G5: 5Y | I5: Last 12M | J5: =Attribution!H3 -> -0.028218615 | K5: =Attribution!I3 -> 0.0024174938 | L5: =Attribution!J3 -> -0.00029171787
A6: Annualised Return | B6: =Metrics!B9 -> 0.065347825 | C6: =Metrics!C9 -> 0.11680939 | D6: =Metrics!D9 -> 0.048684183 | E6: =Metrics!E9 -> 0.092320088 | F6: =Metrics!F9 -> 0.14399517 | G6: =Metrics!G9 -> 0.066245992 | I6: Full Period | J6: =Attribution!H4 -> -0.095224565 | K6: =Attribution!I4 -> 0.0067370522 | L6: =Attribution!J4 -> -0.0007413468
A7: Volatility | B7: =Metrics!B10 -> 0.073806488 | C7: =Metrics!C10 -> 0.077418426 | D7: =Metrics!D10 -> 0.098145805 | E7: =Metrics!E10 -> 0.086607725 | F7: =Metrics!F10 -> 0.085429348 | G7: =Metrics!G10 -> 0.1094657
A8: Sharpe Ratio | B8: =Metrics!B11 -> 0.47892571 | C8: =Metrics!C11 -> 1.1213014 | D8: =Metrics!D11 -> 0.19037169 | E8: =Metrics!E11 -> 0.71956732 | F8: =Metrics!F11 -> 1.3343795 | G8: =Metrics!G11 -> 0.33111735
A9: Tracking Error | B9: =Metrics!B12 -> -0.026972263 | C9: =Metrics!C12 -> -0.027185777 | D9: =Metrics!D13 -> 0.016889131
A10: Max Drawdown (5Y) | D10: =Metrics!D15 -> -0.195022 | G10: =Metrics!G15 -> -0.21149155
J35: Performance. Over the last five years the portfolio returned 4.9% a year, compared with 6.6% for the 60/40 benchmark, a shortfall of about 1.7% a year.
J36: Over the last 12 months it returned 6.5% against 9.2%.
J38: What drove it. The shortfall came almost entirely from asset allocation. The portfolio held about 40% in equities against the benchmark’s 60%,
J39: and equities outperformed bonds over the period.
J40: In the last 12 months, allocation cost 2.8%, while fund selection added a small 0.2%. The choice of funds within each asset class made little difference.
J41: Risk. The portfolio was less volatile than the benchmark (9.8% against 11.0% over five years), and its worst peak-to-trough fall was 19.5% against 21.1%.
J42: Its risk-adjusted return, measured by the Sharpe ratio, was lower at 0.19 against 0.33, because the lower return outweighed the lower risk.
J44: Summary. The portfolio has behaved as a more cautious version of the benchmark. The lower return is the cost of holding less equity,
J45: and the trustees should confirm that this level of risk still matches their objectives.
